punq/__init__.py
punq/_compat.py
punq-0.6.1.dist-info/LICENSE
punq-0.6.1.dist-info/WHEEL
punq-0.6.1.dist-info/METADATA
punq-0.6.1.dist-info/RECORD
