Metadata-Version: 2.1
Name: punq
Version: 0.6.1
Summary: An IOC Container for Python 3.6+
Home-page: https://github.com/bobthemighty/punq
License: MIT
Author: Bob Gregory
Author-email: bob@codefiend.co.uk
Requires-Python: >=3.6.2,<4.0.0
Classifier: Development Status :: 5 - Production/Stable
Classifier: License :: OSI Approved :: MIT License
Classifier: Programming Language :: Python :: 3
Classifier: Programming Language :: Python :: 3.10
Classifier: Programming Language :: Python :: 3.7
Classifier: Programming Language :: Python :: 3.8
Classifier: Programming Language :: Python :: 3.9
Project-URL: Documentation, https://punq.readthedocs.io
Project-URL: Repository, https://github.com/bobthemighty/punq
